{"cameraMode":{"drawMode":0,"name":"Shaded","section":"Shading Mode"},"sceneLighting":false,"audioPlay":false,"sceneViewState":{"showFog":true,"showMaterialUpdate":false,"showSkybox":false,"showFlares":true,"showImageEffects":true,"showParticleSystems":true},"in2DMode":false,"pivot":{"x":4.8913655281066898,"y":0.4539056718349457,"z":0.7363710403442383},"rotation":{"x":0.03778780624270439,"y":-0.0299785565584898,"z":0.0011190548539161683,"w":0.9989416003227234},"size":2.7349371910095217,"orthographic":false}